pyeggs/__init__.py
pyeggs/creator_egg.py
pyeggs/egg_base.py
pyeggs/egg_tracker.py
pyeggs/engine.py
pyeggs/shared.py
pyeggs/splash_screen_egg.py
pyeggs-0.1.0.dist-info/AUTHORS
pyeggs-0.1.0.dist-info/LICENSE
pyeggs-0.1.0.dist-info/METADATA
pyeggs-0.1.0.dist-info/WHEEL
pyeggs-0.1.0.dist-info/pbr.json
pyeggs-0.1.0.dist-info/top_level.txt
pyeggs-0.1.0.dist-info/RECORD
