Metadata-Version: 2.1
Name: pyeggs
Version: 0.1.0
Summary: Hidden Easter Eggs for Python Console Apps
Home-page: https://github.com/Jman420/pyeggs
Author: jman420
Author-email: jman.giannone@gmail.com
License: UNKNOWN
Platform: UNKNOWN
Classifier: Programming Language :: Python :: 3
Classifier: License :: OSI Approved :: MIT License
Classifier: Operating System :: OS Independent
Requires-Python: >=3.8
